QuestionAnsweringBERT/QuestionAnsweringBERT.py
QuestionAnsweringBERT/__init__.py
QuestionAnsweringBERT/test.py
QuestionAnsweringBERT-0.1.dist-info/LICENSE
QuestionAnsweringBERT-0.1.dist-info/METADATA
QuestionAnsweringBERT-0.1.dist-info/WHEEL
QuestionAnsweringBERT-0.1.dist-info/top_level.txt
QuestionAnsweringBERT-0.1.dist-info/RECORD
