Metadata-Version: 2.1
Name: QuestionAnsweringBERT
Version: 0.1
Summary: BERT base question answering implementation
Home-page: https://github.com/swapnanilsharma/QuestionAnsweringBERT
Author: Swapnanil Sharma
Author-email: swapnanilsharma@gmail.com
License: MIT
Keywords: Question Answering,BERT,BERT Embeddings,BERT Transformer,Transformer,Tensorflow
Platform: UNKNOWN
Classifier: License :: OSI Approved :: MIT License
Classifier: Programming Language :: Python :: 3.6
Classifier: Programming Language :: Python :: 3.7
Classifier: Programming Language :: Python :: 3.8
Requires-Dist: numpy
Requires-Dist: tensorflow
Requires-Dist: transformers
